Metadata-Version: 2.1
Name: tb-bot
Version: 0.0.6
Summary: get tor file
Author: Freak
Classifier: Programming Language :: Python :: 3
Classifier: License :: OSI Approved :: MIT License
Classifier: Operating System :: OS Independent
License-File: LICENCE.txt
